{
    "success": true,
    "errors": [],
    "result": {
        "main": {
            "timestamps": [
                "2025-07-05T13:30:00Z",
                "2025-07-05T13:45:00Z",
                "2025-07-05T14:00:00Z",
                "2025-07-05T14:15:00Z",
                "2025-07-05T14:30:00Z",
                "2025-07-05T14:45:00Z",
                "2025-07-05T15:00:00Z",
                "2025-07-05T15:15:00Z",
                "2025-07-05T15:30:00Z",
                "2025-07-05T15:45:00Z",
                "2025-07-05T16:00:00Z",
                "2025-07-05T16:15:00Z",
                "2025-07-05T16:30:00Z",
                "2025-07-05T16:45:00Z",
                "2025-07-05T17:00:00Z",
                "2025-07-05T17:15:00Z",
                "2025-07-05T17:30:00Z",
                "2025-07-05T17:45:00Z",
                "2025-07-05T18:00:00Z",
                "2025-07-05T18:15:00Z",
                "2025-07-05T18:30:00Z",
                "2025-07-05T18:45:00Z",
                "2025-07-05T19:00:00Z",
                "2025-07-05T19:15:00Z",
                "2025-07-05T19:30:00Z",
                "2025-07-05T19:45:00Z",
                "2025-07-05T20:00:00Z",
                "2025-07-05T20:15:00Z",
                "2025-07-05T20:30:00Z",
                "2025-07-05T20:45:00Z",
                "2025-07-05T21:00:00Z",
                "2025-07-05T21:15:00Z",
                "2025-07-05T21:30:00Z",
                "2025-07-05T21:45:00Z",
                "2025-07-05T22:00:00Z",
                "2025-07-05T22:15:00Z",
                "2025-07-05T22:30:00Z",
                "2025-07-05T22:45:00Z",
                "2025-07-05T23:00:00Z",
                "2025-07-05T23:15:00Z",
                "2025-07-05T23:30:00Z",
                "2025-07-05T23:45:00Z",
                "2025-07-06T00:00:00Z",
                "2025-07-06T00:15:00Z",
                "2025-07-06T00:30:00Z",
                "2025-07-06T00:45:00Z",
                "2025-07-06T01:00:00Z",
                "2025-07-06T01:15:00Z",
                "2025-07-06T01:30:00Z",
                "2025-07-06T01:45:00Z",
                "2025-07-06T02:00:00Z",
                "2025-07-06T02:15:00Z",
                "2025-07-06T02:30:00Z",
                "2025-07-06T02:45:00Z",
                "2025-07-06T03:00:00Z",
                "2025-07-06T03:15:00Z",
                "2025-07-06T03:30:00Z",
                "2025-07-06T03:45:00Z",
                "2025-07-06T04:00:00Z",
                "2025-07-06T04:15:00Z",
                "2025-07-06T04:30:00Z",
                "2025-07-06T04:45:00Z",
                "2025-07-06T05:00:00Z",
                "2025-07-06T05:15:00Z",
                "2025-07-06T05:30:00Z",
                "2025-07-06T05:45:00Z",
                "2025-07-06T06:00:00Z",
                "2025-07-06T06:15:00Z",
                "2025-07-06T06:30:00Z",
                "2025-07-06T06:45:00Z",
                "2025-07-06T07:00:00Z",
                "2025-07-06T07:15:00Z",
                "2025-07-06T07:30:00Z",
                "2025-07-06T07:45:00Z",
                "2025-07-06T08:00:00Z",
                "2025-07-06T08:15:00Z",
                "2025-07-06T08:30:00Z",
                "2025-07-06T08:45:00Z",
                "2025-07-06T09:00:00Z",
                "2025-07-06T09:15:00Z",
                "2025-07-06T09:30:00Z",
                "2025-07-06T09:45:00Z",
                "2025-07-06T10:00:00Z",
                "2025-07-06T10:15:00Z",
                "2025-07-06T10:30:00Z",
                "2025-07-06T10:45:00Z",
                "2025-07-06T11:00:00Z",
                "2025-07-06T11:15:00Z",
                "2025-07-06T11:30:00Z",
                "2025-07-06T11:45:00Z",
                "2025-07-06T12:00:00Z",
                "2025-07-06T12:15:00Z",
                "2025-07-06T12:30:00Z",
                "2025-07-06T12:45:00Z",
                "2025-07-06T13:00:00Z",
                "2025-07-06T13:15:00Z",
                "2025-07-06T13:30:00Z",
                "2025-07-06T13:45:00Z",
                "2025-07-06T14:00:00Z",
                "2025-07-06T14:15:00Z",
                "2025-07-06T14:30:00Z",
                "2025-07-06T14:45:00Z",
                "2025-07-06T15:00:00Z",
                "2025-07-06T15:15:00Z",
                "2025-07-06T15:30:00Z",
                "2025-07-06T15:45:00Z",
                "2025-07-06T16:00:00Z",
                "2025-07-06T16:15:00Z",
                "2025-07-06T16:30:00Z",
                "2025-07-06T16:45:00Z",
                "2025-07-06T17:00:00Z",
                "2025-07-06T17:15:00Z",
                "2025-07-06T17:30:00Z",
                "2025-07-06T17:45:00Z",
                "2025-07-06T18:00:00Z",
                "2025-07-06T18:15:00Z",
                "2025-07-06T18:30:00Z",
                "2025-07-06T18:45:00Z",
                "2025-07-06T19:00:00Z",
                "2025-07-06T19:15:00Z",
                "2025-07-06T19:30:00Z",
                "2025-07-06T19:45:00Z",
                "2025-07-06T20:00:00Z",
                "2025-07-06T20:15:00Z",
                "2025-07-06T20:30:00Z",
                "2025-07-06T20:45:00Z",
                "2025-07-06T21:00:00Z",
                "2025-07-06T21:15:00Z",
                "2025-07-06T21:30:00Z",
                "2025-07-06T21:45:00Z",
                "2025-07-06T22:00:00Z",
                "2025-07-06T22:15:00Z",
                "2025-07-06T22:30:00Z",
                "2025-07-06T22:45:00Z",
                "2025-07-06T23:00:00Z",
                "2025-07-06T23:15:00Z",
                "2025-07-06T23:30:00Z",
                "2025-07-06T23:45:00Z",
                "2025-07-07T00:00:00Z",
                "2025-07-07T00:15:00Z",
                "2025-07-07T00:30:00Z",
                "2025-07-07T00:45:00Z",
                "2025-07-07T01:00:00Z",
                "2025-07-07T01:15:00Z",
                "2025-07-07T01:30:00Z",
                "2025-07-07T01:45:00Z",
                "2025-07-07T02:00:00Z",
                "2025-07-07T02:15:00Z",
                "2025-07-07T02:30:00Z",
                "2025-07-07T02:45:00Z",
                "2025-07-07T03:00:00Z",
                "2025-07-07T03:15:00Z",
                "2025-07-07T03:30:00Z",
                "2025-07-07T03:45:00Z",
                "2025-07-07T04:00:00Z",
                "2025-07-07T04:15:00Z",
                "2025-07-07T04:30:00Z",
                "2025-07-07T04:45:00Z",
                "2025-07-07T05:00:00Z",
                "2025-07-07T05:15:00Z",
                "2025-07-07T05:30:00Z",
                "2025-07-07T05:45:00Z",
                "2025-07-07T06:00:00Z",
                "2025-07-07T06:15:00Z",
                "2025-07-07T06:30:00Z",
                "2025-07-07T06:45:00Z",
                "2025-07-07T07:00:00Z",
                "2025-07-07T07:15:00Z",
                "2025-07-07T07:30:00Z",
                "2025-07-07T07:45:00Z",
                "2025-07-07T08:00:00Z",
                "2025-07-07T08:15:00Z",
                "2025-07-07T08:30:00Z",
                "2025-07-07T08:45:00Z",
                "2025-07-07T09:00:00Z",
                "2025-07-07T09:15:00Z",
                "2025-07-07T09:30:00Z",
                "2025-07-07T09:45:00Z",
                "2025-07-07T10:00:00Z",
                "2025-07-07T10:15:00Z",
                "2025-07-07T10:30:00Z",
                "2025-07-07T10:45:00Z",
                "2025-07-07T11:00:00Z",
                "2025-07-07T11:15:00Z",
                "2025-07-07T11:30:00Z",
                "2025-07-07T11:45:00Z",
                "2025-07-07T12:00:00Z",
                "2025-07-07T12:15:00Z",
                "2025-07-07T12:30:00Z",
                "2025-07-07T12:45:00Z",
                "2025-07-07T13:00:00Z"
            ],
            "values": [
                "0.609588",
                "0.582656",
                "0.634414",
                "0.623066",
                "0.653055",
                "0.65871",
                "0.798841",
                "0.691607",
                "0.654543",
                "0.663954",
                "0.690037",
                "0.747307",
                "0.72403",
                "0.742678",
                "0.682785",
                "0.717787",
                "0.710997",
                "0.668311",
                "0.788239",
                "0.72311",
                "0.796793",
                "0.694775",
                "0.76105",
                "0.732105",
                "0.784386",
                "0.711263",
                "0.753831",
                "0.717164",
                "0.75682",
                "0.780186",
                "0.802028",
                "0.887843",
                "0.813724",
                "0.717378",
                "0.679311",
                "0.650066",
                "0.586867",
                "0.487647",
                "0.516601",
                "0.478888",
                "0.418789",
                "0.384864",
                "0.362321",
                "0.31421",
                "0.310042",
                "0.30309",
                "0.259201",
                "0.237908",
                "0.204653",
                "0.185094",
                "0.204508",
                "0.178768",
                "0.143017",
                "0.150757",
                "0.149387",
                "0.125509",
                "0.122898",
                "0.133992",
                "0.130585",
                "0.109109",
                "0.116157",
                "0.128046",
                "0.12045",
                "0.140989",
                "0.157001",
                "0.207616",
                "0.202127",
                "0.231715",
                "0.280159",
                "0.305403",
                "0.341731",
                "0.35216",
                "0.433933",
                "0.389087",
                "0.482099",
                "0.420209",
                "0.483607",
                "0.426872",
                "0.428089",
                "0.569532",
                "0.473059",
                "0.486858",
                "0.543614",
                "0.491496",
                "0.488359",
                "0.529436",
                "0.560405",
                "0.543739",
                "0.538383",
                "0.611174",
                "0.599917",
                "0.633318",
                "0.583181",
                "0.621626",
                "0.639099",
                "0.740145",
                "0.727156",
                "0.737217",
                "0.74093",
                "0.783395",
                "0.819818",
                "0.903178",
                "0.908697",
                "0.863382",
                "1.0",
                "0.91238",
                "0.769364",
                "0.658213",
                "0.758648",
                "0.768049",
                "0.721392",
                "0.78554",
                "0.71777",
                "0.771151",
                "0.864474",
                "0.75533",
                "0.753964",
                "0.776846",
                "0.82625",
                "0.725413",
                "0.725768",
                "0.811631",
                "0.827092",
                "0.837471",
                "0.804011",
                "0.716337",
                "0.793143",
                "0.684684",
                "0.682149",
                "0.618056",
                "0.572583",
                "0.54371",
                "0.492032",
                "0.470278",
                "0.447307",
                "0.357741",
                "0.326954",
                "0.289778",
                "0.301923",
                "0.250009",
                "0.211137",
                "0.213893",
                "0.175569",
                "0.168427",
                "0.149675",
                "0.142833",
                "0.148858",
                "0.222715",
                "0.179882",
                "0.122089",
                "0.112168",
                "0.118307",
                "0.103198",
                "0.120742",
                "0.125814",
                "0.133032",
                "0.129459",
                "0.145657",
                "0.164845",
                "0.189889",
                "0.213078",
                "0.229695",
                "0.260001",
                "0.254714",
                "0.293486",
                "0.340494",
                "0.358821",
                "0.270186",
                "0.271157",
                "0.289854",
                "0.301575",
                "0.32446",
                "0.29277",
                "0.315417",
                "0.301491",
                "0.310973",
                "0.30129",
                "0.289953",
                "0.350713",
                "0.377875",
                "0.349129",
                "0.356117",
                "0.333109",
                "0.346476",
                "0.363202",
                "0.350032",
                "0.432546",
                "0.443238",
                "0.429776",
                "0.451669",
                "0.418291"
            ]
        },
        "previous": {
            "timestamps": [
                "2025-06-28T13:30:00Z",
                "2025-06-28T13:45:00Z",
                "2025-06-28T14:00:00Z",
                "2025-06-28T14:15:00Z",
                "2025-06-28T14:30:00Z",
                "2025-06-28T14:45:00Z",
                "2025-06-28T15:00:00Z",
                "2025-06-28T15:15:00Z",
                "2025-06-28T15:30:00Z",
                "2025-06-28T15:45:00Z",
                "2025-06-28T16:00:00Z",
                "2025-06-28T16:15:00Z",
                "2025-06-28T16:30:00Z",
                "2025-06-28T16:45:00Z",
                "2025-06-28T17:00:00Z",
                "2025-06-28T17:15:00Z",
                "2025-06-28T17:30:00Z",
                "2025-06-28T17:45:00Z",
                "2025-06-28T18:00:00Z",
                "2025-06-28T18:15:00Z",
                "2025-06-28T18:30:00Z",
                "2025-06-28T18:45:00Z",
                "2025-06-28T19:00:00Z",
                "2025-06-28T19:15:00Z",
                "2025-06-28T19:30:00Z",
                "2025-06-28T19:45:00Z",
                "2025-06-28T20:00:00Z",
                "2025-06-28T20:15:00Z",
                "2025-06-28T20:30:00Z",
                "2025-06-28T20:45:00Z",
                "2025-06-28T21:00:00Z",
                "2025-06-28T21:15:00Z",
                "2025-06-28T21:30:00Z",
                "2025-06-28T21:45:00Z",
                "2025-06-28T22:00:00Z",
                "2025-06-28T22:15:00Z",
                "2025-06-28T22:30:00Z",
                "2025-06-28T22:45:00Z",
                "2025-06-28T23:00:00Z",
                "2025-06-28T23:15:00Z",
                "2025-06-28T23:30:00Z",
                "2025-06-28T23:45:00Z",
                "2025-06-29T00:00:00Z",
                "2025-06-29T00:15:00Z",
                "2025-06-29T00:30:00Z",
                "2025-06-29T00:45:00Z",
                "2025-06-29T01:00:00Z",
                "2025-06-29T01:15:00Z",
                "2025-06-29T01:30:00Z",
                "2025-06-29T01:45:00Z",
                "2025-06-29T02:00:00Z",
                "2025-06-29T02:15:00Z",
                "2025-06-29T02:30:00Z",
                "2025-06-29T02:45:00Z",
                "2025-06-29T03:00:00Z",
                "2025-06-29T03:15:00Z",
                "2025-06-29T03:30:00Z",
                "2025-06-29T03:45:00Z",
                "2025-06-29T04:00:00Z",
                "2025-06-29T04:15:00Z",
                "2025-06-29T04:30:00Z",
                "2025-06-29T04:45:00Z",
                "2025-06-29T05:00:00Z",
                "2025-06-29T05:15:00Z",
                "2025-06-29T05:30:00Z",
                "2025-06-29T05:45:00Z",
                "2025-06-29T06:00:00Z",
                "2025-06-29T06:15:00Z",
                "2025-06-29T06:30:00Z",
                "2025-06-29T06:45:00Z",
                "2025-06-29T07:00:00Z",
                "2025-06-29T07:15:00Z",
                "2025-06-29T07:30:00Z",
                "2025-06-29T07:45:00Z",
                "2025-06-29T08:00:00Z",
                "2025-06-29T08:15:00Z",
                "2025-06-29T08:30:00Z",
                "2025-06-29T08:45:00Z",
                "2025-06-29T09:00:00Z",
                "2025-06-29T09:15:00Z",
                "2025-06-29T09:30:00Z",
                "2025-06-29T09:45:00Z",
                "2025-06-29T10:00:00Z",
                "2025-06-29T10:15:00Z",
                "2025-06-29T10:30:00Z",
                "2025-06-29T10:45:00Z",
                "2025-06-29T11:00:00Z",
                "2025-06-29T11:15:00Z",
                "2025-06-29T11:30:00Z",
                "2025-06-29T11:45:00Z",
                "2025-06-29T12:00:00Z",
                "2025-06-29T12:15:00Z",
                "2025-06-29T12:30:00Z",
                "2025-06-29T12:45:00Z",
                "2025-06-29T13:00:00Z",
                "2025-06-29T13:15:00Z",
                "2025-06-29T13:30:00Z",
                "2025-06-29T13:45:00Z",
                "2025-06-29T14:00:00Z",
                "2025-06-29T14:15:00Z",
                "2025-06-29T14:30:00Z",
                "2025-06-29T14:45:00Z",
                "2025-06-29T15:00:00Z",
                "2025-06-29T15:15:00Z",
                "2025-06-29T15:30:00Z",
                "2025-06-29T15:45:00Z",
                "2025-06-29T16:00:00Z",
                "2025-06-29T16:15:00Z",
                "2025-06-29T16:30:00Z",
                "2025-06-29T16:45:00Z",
                "2025-06-29T17:00:00Z",
                "2025-06-29T17:15:00Z",
                "2025-06-29T17:30:00Z",
                "2025-06-29T17:45:00Z",
                "2025-06-29T18:00:00Z",
                "2025-06-29T18:15:00Z",
                "2025-06-29T18:30:00Z",
                "2025-06-29T18:45:00Z",
                "2025-06-29T19:00:00Z",
                "2025-06-29T19:15:00Z",
                "2025-06-29T19:30:00Z",
                "2025-06-29T19:45:00Z",
                "2025-06-29T20:00:00Z",
                "2025-06-29T20:15:00Z",
                "2025-06-29T20:30:00Z",
                "2025-06-29T20:45:00Z",
                "2025-06-29T21:00:00Z",
                "2025-06-29T21:15:00Z",
                "2025-06-29T21:30:00Z",
                "2025-06-29T21:45:00Z",
                "2025-06-29T22:00:00Z",
                "2025-06-29T22:15:00Z",
                "2025-06-29T22:30:00Z",
                "2025-06-29T22:45:00Z",
                "2025-06-29T23:00:00Z",
                "2025-06-29T23:15:00Z",
                "2025-06-29T23:30:00Z",
                "2025-06-29T23:45:00Z",
                "2025-06-30T00:00:00Z",
                "2025-06-30T00:15:00Z",
                "2025-06-30T00:30:00Z",
                "2025-06-30T00:45:00Z",
                "2025-06-30T01:00:00Z",
                "2025-06-30T01:15:00Z",
                "2025-06-30T01:30:00Z",
                "2025-06-30T01:45:00Z",
                "2025-06-30T02:00:00Z",
                "2025-06-30T02:15:00Z",
                "2025-06-30T02:30:00Z",
                "2025-06-30T02:45:00Z",
                "2025-06-30T03:00:00Z",
                "2025-06-30T03:15:00Z",
                "2025-06-30T03:30:00Z",
                "2025-06-30T03:45:00Z",
                "2025-06-30T04:00:00Z",
                "2025-06-30T04:15:00Z",
                "2025-06-30T04:30:00Z",
                "2025-06-30T04:45:00Z",
                "2025-06-30T05:00:00Z",
                "2025-06-30T05:15:00Z",
                "2025-06-30T05:30:00Z",
                "2025-06-30T05:45:00Z",
                "2025-06-30T06:00:00Z",
                "2025-06-30T06:15:00Z",
                "2025-06-30T06:30:00Z",
                "2025-06-30T06:45:00Z",
                "2025-06-30T07:00:00Z",
                "2025-06-30T07:15:00Z",
                "2025-06-30T07:30:00Z",
                "2025-06-30T07:45:00Z",
                "2025-06-30T08:00:00Z",
                "2025-06-30T08:15:00Z",
                "2025-06-30T08:30:00Z",
                "2025-06-30T08:45:00Z",
                "2025-06-30T09:00:00Z",
                "2025-06-30T09:15:00Z",
                "2025-06-30T09:30:00Z",
                "2025-06-30T09:45:00Z",
                "2025-06-30T10:00:00Z",
                "2025-06-30T10:15:00Z",
                "2025-06-30T10:30:00Z",
                "2025-06-30T10:45:00Z",
                "2025-06-30T11:00:00Z",
                "2025-06-30T11:15:00Z",
                "2025-06-30T11:30:00Z",
                "2025-06-30T11:45:00Z",
                "2025-06-30T12:00:00Z",
                "2025-06-30T12:15:00Z",
                "2025-06-30T12:30:00Z",
                "2025-06-30T12:45:00Z",
                "2025-06-30T13:00:00Z"
            ],
            "values": [
                "0.55317",
                "0.578092",
                "0.582912",
                "0.514064",
                "0.487169",
                "0.493541",
                "0.519194",
                "0.541274",
                "0.565883",
                "0.472744",
                "0.547392",
                "0.523093",
                "0.506018",
                "0.619403",
                "0.611367",
                "0.618079",
                "0.60496",
                "0.54803",
                "0.526667",
                "0.552794",
                "0.638282",
                "0.617809",
                "0.577858",
                "0.558952",
                "0.612529",
                "0.599166",
                "0.673047",
                "0.700743",
                "0.737796",
                "0.769114",
                "0.660771",
                "0.72241",
                "0.740969",
                "0.72823",
                "0.778599",
                "0.636899",
                "0.607603",
                "0.554524",
                "0.560983",
                "0.519491",
                "0.464089",
                "0.43034",
                "0.424384",
                "0.393758",
                "0.34994",
                "0.293499",
                "0.266197",
                "0.271554",
                "0.225784",
                "0.225308",
                "0.211899",
                "0.188894",
                "0.17932",
                "0.170154",
                "0.162743",
                "0.169686",
                "0.148247",
                "0.141075",
                "0.149123",
                "0.151307",
                "0.157773",
                "0.160701",
                "0.154183",
                "0.166132",
                "0.179236",
                "0.193417",
                "0.214136",
                "0.210441",
                "0.263633",
                "0.264876",
                "0.308854",
                "0.374832",
                "0.32941",
                "0.319929",
                "0.331148",
                "0.344595",
                "0.383119",
                "0.393984",
                "0.399559",
                "0.419493",
                "0.398145",
                "0.414734",
                "0.424957",
                "0.530786",
                "0.564321",
                "0.493394",
                "0.532713",
                "0.462679",
                "0.48506",
                "0.492619",
                "0.606234",
                "0.543412",
                "0.581078",
                "0.622754",
                "0.695903",
                "0.680913",
                "0.667804",
                "0.77867",
                "0.664891",
                "0.665485",
                "0.641232",
                "0.653919",
                "0.613479",
                "0.605722",
                "0.650595",
                "0.581237",
                "0.614567",
                "0.73699",
                "0.647216",
                "0.70554",
                "0.705115",
                "0.735744",
                "0.727948",
                "0.660226",
                "0.66708",
                "0.698526",
                "0.704611",
                "0.737763",
                "0.792683",
                "0.758443",
                "0.72359",
                "0.763614",
                "0.860394",
                "0.782889",
                "0.793443",
                "0.742457",
                "0.762943",
                "0.752971",
                "0.762747",
                "0.732929",
                "0.711873",
                "0.655659",
                "0.560763",
                "0.545346",
                "0.525518",
                "0.43386",
                "0.470182",
                "0.425399",
                "0.310526",
                "0.294439",
                "0.231469",
                "0.22383",
                "0.187866",
                "0.182659",
                "0.167377",
                "0.147185",
                "0.141364",
                "0.137512",
                "0.117323",
                "0.121543",
                "0.102303",
                "0.11113",
                "0.104213",
                "0.10266",
                "0.111237",
                "0.122293",
                "0.114211",
                "0.126276",
                "0.150063",
                "0.176677",
                "0.222192",
                "0.218092",
                "0.245659",
                "0.271577",
                "0.275358",
                "0.279862",
                "0.297209",
                "0.27287",
                "0.274026",
                "0.291062",
                "0.29112",
                "0.270717",
                "0.267616",
                "0.342663",
                "0.293645",
                "0.303",
                "0.303339",
                "0.276382",
                "0.306882",
                "0.327567",
                "0.315516",
                "0.323195",
                "0.329649",
                "0.315738",
                "0.301023",
                "0.291157",
                "0.284977",
                "0.333611",
                "0.317672",
                "0.351526",
                "0.341586"
            ]
        },
        "meta": {
            "dateRange": [
                {
                    "startTime": "2025-07-05T13:30:00Z",
                    "endTime": "2025-07-07T13:30:00Z"
                },
                {
                    "startTime": "2025-06-28T13:30:00Z",
                    "endTime": "2025-06-30T13:30:00Z"
                }
            ],
            "confidenceInfo": {
                "level": 5,
                "annotations": []
            },
            "normalization": "MIN0_MAX",
            "aggInterval": "FIFTEEN_MINUTES",
            "lastUpdated": "2025-07-07T13:00:00Z",
            "units": [
                {
                    "name": "*",
                    "value": "bytes"
                }
            ]
        }
    }
}