{
    "success": true,
    "errors": [],
    "result": {
        "main": {
            "timestamps": [
                "2025-07-05T13:30:00Z",
                "2025-07-05T13:45:00Z",
                "2025-07-05T14:00:00Z",
                "2025-07-05T14:15:00Z",
                "2025-07-05T14:30:00Z",
                "2025-07-05T14:45:00Z",
                "2025-07-05T15:00:00Z",
                "2025-07-05T15:15:00Z",
                "2025-07-05T15:30:00Z",
                "2025-07-05T15:45:00Z",
                "2025-07-05T16:00:00Z",
                "2025-07-05T16:15:00Z",
                "2025-07-05T16:30:00Z",
                "2025-07-05T16:45:00Z",
                "2025-07-05T17:00:00Z",
                "2025-07-05T17:15:00Z",
                "2025-07-05T17:30:00Z",
                "2025-07-05T17:45:00Z",
                "2025-07-05T18:00:00Z",
                "2025-07-05T18:15:00Z",
                "2025-07-05T18:30:00Z",
                "2025-07-05T18:45:00Z",
                "2025-07-05T19:00:00Z",
                "2025-07-05T19:15:00Z",
                "2025-07-05T19:30:00Z",
                "2025-07-05T19:45:00Z",
                "2025-07-05T20:00:00Z",
                "2025-07-05T20:15:00Z",
                "2025-07-05T20:30:00Z",
                "2025-07-05T20:45:00Z",
                "2025-07-05T21:00:00Z",
                "2025-07-05T21:15:00Z",
                "2025-07-05T21:30:00Z",
                "2025-07-05T21:45:00Z",
                "2025-07-05T22:00:00Z",
                "2025-07-05T22:15:00Z",
                "2025-07-05T22:30:00Z",
                "2025-07-05T22:45:00Z",
                "2025-07-05T23:00:00Z",
                "2025-07-05T23:15:00Z",
                "2025-07-05T23:30:00Z",
                "2025-07-05T23:45:00Z",
                "2025-07-06T00:00:00Z",
                "2025-07-06T00:15:00Z",
                "2025-07-06T00:30:00Z",
                "2025-07-06T00:45:00Z",
                "2025-07-06T01:00:00Z",
                "2025-07-06T01:15:00Z",
                "2025-07-06T01:30:00Z",
                "2025-07-06T01:45:00Z",
                "2025-07-06T02:00:00Z",
                "2025-07-06T02:15:00Z",
                "2025-07-06T02:30:00Z",
                "2025-07-06T02:45:00Z",
                "2025-07-06T03:00:00Z",
                "2025-07-06T03:15:00Z",
                "2025-07-06T03:30:00Z",
                "2025-07-06T03:45:00Z",
                "2025-07-06T04:00:00Z",
                "2025-07-06T04:15:00Z",
                "2025-07-06T04:30:00Z",
                "2025-07-06T04:45:00Z",
                "2025-07-06T05:00:00Z",
                "2025-07-06T05:15:00Z",
                "2025-07-06T05:30:00Z",
                "2025-07-06T05:45:00Z",
                "2025-07-06T06:00:00Z",
                "2025-07-06T06:15:00Z",
                "2025-07-06T06:30:00Z",
                "2025-07-06T06:45:00Z",
                "2025-07-06T07:00:00Z",
                "2025-07-06T07:15:00Z",
                "2025-07-06T07:30:00Z",
                "2025-07-06T07:45:00Z",
                "2025-07-06T08:00:00Z",
                "2025-07-06T08:15:00Z",
                "2025-07-06T08:30:00Z",
                "2025-07-06T08:45:00Z",
                "2025-07-06T09:00:00Z",
                "2025-07-06T09:15:00Z",
                "2025-07-06T09:30:00Z",
                "2025-07-06T09:45:00Z",
                "2025-07-06T10:00:00Z",
                "2025-07-06T10:15:00Z",
                "2025-07-06T10:30:00Z",
                "2025-07-06T10:45:00Z",
                "2025-07-06T11:00:00Z",
                "2025-07-06T11:15:00Z",
                "2025-07-06T11:30:00Z",
                "2025-07-06T11:45:00Z",
                "2025-07-06T12:00:00Z",
                "2025-07-06T12:15:00Z",
                "2025-07-06T12:30:00Z",
                "2025-07-06T12:45:00Z",
                "2025-07-06T13:00:00Z",
                "2025-07-06T13:15:00Z",
                "2025-07-06T13:30:00Z",
                "2025-07-06T13:45:00Z",
                "2025-07-06T14:00:00Z",
                "2025-07-06T14:15:00Z",
                "2025-07-06T14:30:00Z",
                "2025-07-06T14:45:00Z",
                "2025-07-06T15:00:00Z",
                "2025-07-06T15:15:00Z",
                "2025-07-06T15:30:00Z",
                "2025-07-06T15:45:00Z",
                "2025-07-06T16:00:00Z",
                "2025-07-06T16:15:00Z",
                "2025-07-06T16:30:00Z",
                "2025-07-06T16:45:00Z",
                "2025-07-06T17:00:00Z",
                "2025-07-06T17:15:00Z",
                "2025-07-06T17:30:00Z",
                "2025-07-06T17:45:00Z",
                "2025-07-06T18:00:00Z",
                "2025-07-06T18:15:00Z",
                "2025-07-06T18:30:00Z",
                "2025-07-06T18:45:00Z",
                "2025-07-06T19:00:00Z",
                "2025-07-06T19:15:00Z",
                "2025-07-06T19:30:00Z",
                "2025-07-06T19:45:00Z",
                "2025-07-06T20:00:00Z",
                "2025-07-06T20:15:00Z",
                "2025-07-06T20:30:00Z",
                "2025-07-06T20:45:00Z",
                "2025-07-06T21:00:00Z",
                "2025-07-06T21:15:00Z",
                "2025-07-06T21:30:00Z",
                "2025-07-06T21:45:00Z",
                "2025-07-06T22:00:00Z",
                "2025-07-06T22:15:00Z",
                "2025-07-06T22:30:00Z",
                "2025-07-06T22:45:00Z",
                "2025-07-06T23:00:00Z",
                "2025-07-06T23:15:00Z",
                "2025-07-06T23:30:00Z",
                "2025-07-06T23:45:00Z",
                "2025-07-07T00:00:00Z",
                "2025-07-07T00:15:00Z",
                "2025-07-07T00:30:00Z",
                "2025-07-07T00:45:00Z",
                "2025-07-07T01:00:00Z",
                "2025-07-07T01:15:00Z",
                "2025-07-07T01:30:00Z",
                "2025-07-07T01:45:00Z",
                "2025-07-07T02:00:00Z",
                "2025-07-07T02:15:00Z",
                "2025-07-07T02:30:00Z",
                "2025-07-07T02:45:00Z",
                "2025-07-07T03:00:00Z",
                "2025-07-07T03:15:00Z",
                "2025-07-07T03:30:00Z",
                "2025-07-07T03:45:00Z",
                "2025-07-07T04:00:00Z",
                "2025-07-07T04:15:00Z",
                "2025-07-07T04:30:00Z",
                "2025-07-07T04:45:00Z",
                "2025-07-07T05:00:00Z",
                "2025-07-07T05:15:00Z",
                "2025-07-07T05:30:00Z",
                "2025-07-07T05:45:00Z",
                "2025-07-07T06:00:00Z",
                "2025-07-07T06:15:00Z",
                "2025-07-07T06:30:00Z",
                "2025-07-07T06:45:00Z",
                "2025-07-07T07:00:00Z",
                "2025-07-07T07:15:00Z",
                "2025-07-07T07:30:00Z",
                "2025-07-07T07:45:00Z",
                "2025-07-07T08:00:00Z",
                "2025-07-07T08:15:00Z",
                "2025-07-07T08:30:00Z",
                "2025-07-07T08:45:00Z",
                "2025-07-07T09:00:00Z",
                "2025-07-07T09:15:00Z",
                "2025-07-07T09:30:00Z",
                "2025-07-07T09:45:00Z",
                "2025-07-07T10:00:00Z",
                "2025-07-07T10:15:00Z",
                "2025-07-07T10:30:00Z",
                "2025-07-07T10:45:00Z",
                "2025-07-07T11:00:00Z",
                "2025-07-07T11:15:00Z",
                "2025-07-07T11:30:00Z",
                "2025-07-07T11:45:00Z",
                "2025-07-07T12:00:00Z",
                "2025-07-07T12:15:00Z",
                "2025-07-07T12:30:00Z",
                "2025-07-07T12:45:00Z",
                "2025-07-07T13:00:00Z",
                "2025-07-07T13:15:00Z"
            ],
            "values": [
                "0.687358",
                "0.676594",
                "0.695593",
                "0.730628",
                "0.756851",
                "0.758909",
                "0.778244",
                "0.694405",
                "0.735581",
                "0.765975",
                "0.798842",
                "0.842532",
                "0.758596",
                "0.803821",
                "0.777354",
                "0.831644",
                "0.849727",
                "0.821202",
                "0.806705",
                "0.804271",
                "0.800204",
                "0.793393",
                "0.792618",
                "0.834104",
                "0.857831",
                "0.815842",
                "0.855239",
                "0.885336",
                "0.900267",
                "0.962478",
                "0.875063",
                "0.926814",
                "0.949103",
                "0.899755",
                "0.792867",
                "0.737385",
                "0.721776",
                "0.652284",
                "0.643815",
                "0.599441",
                "0.568693",
                "0.520753",
                "0.547772",
                "0.498885",
                "0.488384",
                "0.477531",
                "0.45049",
                "0.398656",
                "0.381733",
                "0.382932",
                "0.378765",
                "0.368333",
                "0.327622",
                "0.345621",
                "0.367727",
                "0.314567",
                "0.32408",
                "0.313386",
                "0.349993",
                "0.304518",
                "0.318649",
                "0.35206",
                "0.336352",
                "0.364227",
                "0.373358",
                "0.402642",
                "0.398927",
                "0.408231",
                "0.497651",
                "0.480463",
                "0.540049",
                "0.517379",
                "0.608718",
                "0.550938",
                "0.601792",
                "0.587601",
                "0.603812",
                "0.615436",
                "0.608992",
                "0.71949",
                "0.622107",
                "0.654624",
                "0.684706",
                "0.673193",
                "0.655432",
                "0.71396",
                "0.720329",
                "0.736037",
                "0.676392",
                "0.719414",
                "0.692398",
                "0.696871",
                "0.691324",
                "0.789717",
                "0.741049",
                "0.756044",
                "0.755922",
                "0.750121",
                "0.76568",
                "0.782106",
                "0.833549",
                "0.787113",
                "0.838521",
                "0.861346",
                "0.792017",
                "0.850953",
                "0.818261",
                "0.778236",
                "0.83523",
                "0.829115",
                "0.816377",
                "0.942511",
                "0.870599",
                "0.876925",
                "0.877371",
                "0.856324",
                "0.886772",
                "0.890213",
                "0.969184",
                "0.924896",
                "0.916818",
                "0.95378",
                "0.95862",
                "0.993527",
                "0.953651",
                "0.881489",
                "0.947157",
                "0.878584",
                "0.865269",
                "0.805039",
                "0.843671",
                "0.773022",
                "0.721908",
                "0.713039",
                "0.645345",
                "0.561518",
                "0.526134",
                "0.482538",
                "0.509567",
                "0.477995",
                "0.449486",
                "0.443776",
                "0.407243",
                "0.399641",
                "0.360791",
                "0.336095",
                "0.343225",
                "0.326992",
                "0.31805",
                "0.350543",
                "0.329901",
                "0.332434",
                "0.324203",
                "0.335286",
                "0.347256",
                "0.351856",
                "0.354224",
                "0.3906",
                "0.39384",
                "0.418583",
                "0.44117",
                "0.45313",
                "0.50035",
                "0.517735",
                "0.507857",
                "0.526953",
                "0.563494",
                "0.583428",
                "0.554153",
                "0.56496",
                "0.586635",
                "0.636653",
                "0.583506",
                "0.592822",
                "0.594193",
                "0.590539",
                "0.608889",
                "0.617667",
                "0.629713",
                "0.714182",
                "0.64243",
                "0.633915",
                "0.648094",
                "0.647273",
                "0.64529",
                "0.691128",
                "0.726224",
                "0.6512",
                "0.674927",
                "0.676542",
                "0.693389",
                "0.697681"
            ]
        },
        "previous": {
            "timestamps": [
                "2025-06-28T13:30:00Z",
                "2025-06-28T13:45:00Z",
                "2025-06-28T14:00:00Z",
                "2025-06-28T14:15:00Z",
                "2025-06-28T14:30:00Z",
                "2025-06-28T14:45:00Z",
                "2025-06-28T15:00:00Z",
                "2025-06-28T15:15:00Z",
                "2025-06-28T15:30:00Z",
                "2025-06-28T15:45:00Z",
                "2025-06-28T16:00:00Z",
                "2025-06-28T16:15:00Z",
                "2025-06-28T16:30:00Z",
                "2025-06-28T16:45:00Z",
                "2025-06-28T17:00:00Z",
                "2025-06-28T17:15:00Z",
                "2025-06-28T17:30:00Z",
                "2025-06-28T17:45:00Z",
                "2025-06-28T18:00:00Z",
                "2025-06-28T18:15:00Z",
                "2025-06-28T18:30:00Z",
                "2025-06-28T18:45:00Z",
                "2025-06-28T19:00:00Z",
                "2025-06-28T19:15:00Z",
                "2025-06-28T19:30:00Z",
                "2025-06-28T19:45:00Z",
                "2025-06-28T20:00:00Z",
                "2025-06-28T20:15:00Z",
                "2025-06-28T20:30:00Z",
                "2025-06-28T20:45:00Z",
                "2025-06-28T21:00:00Z",
                "2025-06-28T21:15:00Z",
                "2025-06-28T21:30:00Z",
                "2025-06-28T21:45:00Z",
                "2025-06-28T22:00:00Z",
                "2025-06-28T22:15:00Z",
                "2025-06-28T22:30:00Z",
                "2025-06-28T22:45:00Z",
                "2025-06-28T23:00:00Z",
                "2025-06-28T23:15:00Z",
                "2025-06-28T23:30:00Z",
                "2025-06-28T23:45:00Z",
                "2025-06-29T00:00:00Z",
                "2025-06-29T00:15:00Z",
                "2025-06-29T00:30:00Z",
                "2025-06-29T00:45:00Z",
                "2025-06-29T01:00:00Z",
                "2025-06-29T01:15:00Z",
                "2025-06-29T01:30:00Z",
                "2025-06-29T01:45:00Z",
                "2025-06-29T02:00:00Z",
                "2025-06-29T02:15:00Z",
                "2025-06-29T02:30:00Z",
                "2025-06-29T02:45:00Z",
                "2025-06-29T03:00:00Z",
                "2025-06-29T03:15:00Z",
                "2025-06-29T03:30:00Z",
                "2025-06-29T03:45:00Z",
                "2025-06-29T04:00:00Z",
                "2025-06-29T04:15:00Z",
                "2025-06-29T04:30:00Z",
                "2025-06-29T04:45:00Z",
                "2025-06-29T05:00:00Z",
                "2025-06-29T05:15:00Z",
                "2025-06-29T05:30:00Z",
                "2025-06-29T05:45:00Z",
                "2025-06-29T06:00:00Z",
                "2025-06-29T06:15:00Z",
                "2025-06-29T06:30:00Z",
                "2025-06-29T06:45:00Z",
                "2025-06-29T07:00:00Z",
                "2025-06-29T07:15:00Z",
                "2025-06-29T07:30:00Z",
                "2025-06-29T07:45:00Z",
                "2025-06-29T08:00:00Z",
                "2025-06-29T08:15:00Z",
                "2025-06-29T08:30:00Z",
                "2025-06-29T08:45:00Z",
                "2025-06-29T09:00:00Z",
                "2025-06-29T09:15:00Z",
                "2025-06-29T09:30:00Z",
                "2025-06-29T09:45:00Z",
                "2025-06-29T10:00:00Z",
                "2025-06-29T10:15:00Z",
                "2025-06-29T10:30:00Z",
                "2025-06-29T10:45:00Z",
                "2025-06-29T11:00:00Z",
                "2025-06-29T11:15:00Z",
                "2025-06-29T11:30:00Z",
                "2025-06-29T11:45:00Z",
                "2025-06-29T12:00:00Z",
                "2025-06-29T12:15:00Z",
                "2025-06-29T12:30:00Z",
                "2025-06-29T12:45:00Z",
                "2025-06-29T13:00:00Z",
                "2025-06-29T13:15:00Z",
                "2025-06-29T13:30:00Z",
                "2025-06-29T13:45:00Z",
                "2025-06-29T14:00:00Z",
                "2025-06-29T14:15:00Z",
                "2025-06-29T14:30:00Z",
                "2025-06-29T14:45:00Z",
                "2025-06-29T15:00:00Z",
                "2025-06-29T15:15:00Z",
                "2025-06-29T15:30:00Z",
                "2025-06-29T15:45:00Z",
                "2025-06-29T16:00:00Z",
                "2025-06-29T16:15:00Z",
                "2025-06-29T16:30:00Z",
                "2025-06-29T16:45:00Z",
                "2025-06-29T17:00:00Z",
                "2025-06-29T17:15:00Z",
                "2025-06-29T17:30:00Z",
                "2025-06-29T17:45:00Z",
                "2025-06-29T18:00:00Z",
                "2025-06-29T18:15:00Z",
                "2025-06-29T18:30:00Z",
                "2025-06-29T18:45:00Z",
                "2025-06-29T19:00:00Z",
                "2025-06-29T19:15:00Z",
                "2025-06-29T19:30:00Z",
                "2025-06-29T19:45:00Z",
                "2025-06-29T20:00:00Z",
                "2025-06-29T20:15:00Z",
                "2025-06-29T20:30:00Z",
                "2025-06-29T20:45:00Z",
                "2025-06-29T21:00:00Z",
                "2025-06-29T21:15:00Z",
                "2025-06-29T21:30:00Z",
                "2025-06-29T21:45:00Z",
                "2025-06-29T22:00:00Z",
                "2025-06-29T22:15:00Z",
                "2025-06-29T22:30:00Z",
                "2025-06-29T22:45:00Z",
                "2025-06-29T23:00:00Z",
                "2025-06-29T23:15:00Z",
                "2025-06-29T23:30:00Z",
                "2025-06-29T23:45:00Z",
                "2025-06-30T00:00:00Z",
                "2025-06-30T00:15:00Z",
                "2025-06-30T00:30:00Z",
                "2025-06-30T00:45:00Z",
                "2025-06-30T01:00:00Z",
                "2025-06-30T01:15:00Z",
                "2025-06-30T01:30:00Z",
                "2025-06-30T01:45:00Z",
                "2025-06-30T02:00:00Z",
                "2025-06-30T02:15:00Z",
                "2025-06-30T02:30:00Z",
                "2025-06-30T02:45:00Z",
                "2025-06-30T03:00:00Z",
                "2025-06-30T03:15:00Z",
                "2025-06-30T03:30:00Z",
                "2025-06-30T03:45:00Z",
                "2025-06-30T04:00:00Z",
                "2025-06-30T04:15:00Z",
                "2025-06-30T04:30:00Z",
                "2025-06-30T04:45:00Z",
                "2025-06-30T05:00:00Z",
                "2025-06-30T05:15:00Z",
                "2025-06-30T05:30:00Z",
                "2025-06-30T05:45:00Z",
                "2025-06-30T06:00:00Z",
                "2025-06-30T06:15:00Z",
                "2025-06-30T06:30:00Z",
                "2025-06-30T06:45:00Z",
                "2025-06-30T07:00:00Z",
                "2025-06-30T07:15:00Z",
                "2025-06-30T07:30:00Z",
                "2025-06-30T07:45:00Z",
                "2025-06-30T08:00:00Z",
                "2025-06-30T08:15:00Z",
                "2025-06-30T08:30:00Z",
                "2025-06-30T08:45:00Z",
                "2025-06-30T09:00:00Z",
                "2025-06-30T09:15:00Z",
                "2025-06-30T09:30:00Z",
                "2025-06-30T09:45:00Z",
                "2025-06-30T10:00:00Z",
                "2025-06-30T10:15:00Z",
                "2025-06-30T10:30:00Z",
                "2025-06-30T10:45:00Z",
                "2025-06-30T11:00:00Z",
                "2025-06-30T11:15:00Z",
                "2025-06-30T11:30:00Z",
                "2025-06-30T11:45:00Z",
                "2025-06-30T12:00:00Z",
                "2025-06-30T12:15:00Z",
                "2025-06-30T12:30:00Z",
                "2025-06-30T12:45:00Z",
                "2025-06-30T13:00:00Z",
                "2025-06-30T13:15:00Z"
            ],
            "values": [
                "0.716481",
                "0.707115",
                "0.675283",
                "0.691327",
                "0.661447",
                "0.693054",
                "0.713871",
                "0.70046",
                "0.707566",
                "0.661771",
                "0.686688",
                "0.676232",
                "0.699216",
                "0.739587",
                "0.722489",
                "0.723405",
                "0.742852",
                "0.726467",
                "0.728165",
                "0.786257",
                "0.791701",
                "0.763297",
                "0.771794",
                "0.775829",
                "0.786867",
                "0.771579",
                "0.780086",
                "0.851194",
                "0.881353",
                "0.928313",
                "0.785613",
                "0.832596",
                "0.839052",
                "0.770194",
                "0.835742",
                "0.781286",
                "0.709684",
                "0.63106",
                "0.643766",
                "0.643931",
                "0.583984",
                "0.498356",
                "0.548301",
                "0.493941",
                "0.492367",
                "0.44762",
                "0.417029",
                "0.370781",
                "0.361004",
                "0.356048",
                "0.334541",
                "0.343528",
                "0.31947",
                "0.328735",
                "0.354271",
                "0.328074",
                "0.329797",
                "0.313345",
                "0.331122",
                "0.311118",
                "0.324093",
                "0.33991",
                "0.354389",
                "0.38042",
                "0.420234",
                "0.391719",
                "0.390565",
                "0.398089",
                "0.456826",
                "0.458565",
                "0.502397",
                "0.510287",
                "0.531779",
                "0.552213",
                "0.571185",
                "0.582838",
                "0.656599",
                "0.624317",
                "0.626335",
                "0.640048",
                "0.609229",
                "0.659992",
                "0.680491",
                "0.667552",
                "0.674118",
                "0.68381",
                "0.675798",
                "0.665243",
                "0.669844",
                "0.704812",
                "0.78761",
                "0.715235",
                "0.73621",
                "0.737699",
                "0.770971",
                "0.736603",
                "0.742432",
                "0.790504",
                "0.749679",
                "0.775533",
                "0.76082",
                "0.812322",
                "0.7801",
                "0.785667",
                "0.815251",
                "0.803011",
                "0.855639",
                "0.85745",
                "0.850023",
                "0.829885",
                "0.857593",
                "0.87936",
                "0.984081",
                "0.939607",
                "0.913536",
                "0.90147",
                "0.90179",
                "0.917756",
                "0.947868",
                "0.985969",
                "0.937817",
                "0.942541",
                "1.0",
                "0.953883",
                "0.970436",
                "0.945315",
                "0.943013",
                "0.912073",
                "0.881264",
                "0.841101",
                "0.836988",
                "0.757631",
                "0.70299",
                "0.749036",
                "0.582499",
                "0.522162",
                "0.506967",
                "0.478425",
                "0.495688",
                "0.470104",
                "0.411489",
                "0.402131",
                "0.355831",
                "0.339265",
                "0.331062",
                "0.318513",
                "0.297089",
                "0.290951",
                "0.270094",
                "0.306697",
                "0.289643",
                "0.297407",
                "0.344608",
                "0.325226",
                "0.310355",
                "0.357046",
                "0.343425",
                "0.381704",
                "0.40253",
                "0.408883",
                "0.453993",
                "0.471942",
                "0.448504",
                "0.478552",
                "0.48519",
                "0.532289",
                "0.599508",
                "0.563874",
                "0.578616",
                "0.593743",
                "0.584697",
                "0.577447",
                "0.597263",
                "0.622879",
                "0.527903",
                "0.534431",
                "0.521878",
                "0.517386",
                "0.548942",
                "0.555949",
                "0.562346",
                "0.608817",
                "0.59335",
                "0.560235",
                "0.537101",
                "0.565374",
                "0.584814",
                "0.58721",
                "0.600477",
                "0.609648",
                "0.595903",
                "0.576963"
            ]
        },
        "meta": {
            "dateRange": [
                {
                    "startTime": "2025-07-05T13:30:00Z",
                    "endTime": "2025-07-07T13:30:00Z"
                },
                {
                    "startTime": "2025-06-28T13:30:00Z",
                    "endTime": "2025-06-30T13:30:00Z"
                }
            ],
            "confidenceInfo": {
                "level": 5,
                "annotations": []
            },
            "normalization": "MIN0_MAX",
            "aggInterval": "FIFTEEN_MINUTES",
            "lastUpdated": "2025-07-07T13:15:00Z",
            "units": [
                {
                    "name": "*",
                    "value": "bytes"
                }
            ]
        }
    }
}