{
    "success": true,
    "errors": [],
    "result": {
        "main": {
            "timestamps": [
                "2025-07-05T13:45:00Z",
                "2025-07-05T14:00:00Z",
                "2025-07-05T14:15:00Z",
                "2025-07-05T14:30:00Z",
                "2025-07-05T14:45:00Z",
                "2025-07-05T15:00:00Z",
                "2025-07-05T15:15:00Z",
                "2025-07-05T15:30:00Z",
                "2025-07-05T15:45:00Z",
                "2025-07-05T16:00:00Z",
                "2025-07-05T16:15:00Z",
                "2025-07-05T16:30:00Z",
                "2025-07-05T16:45:00Z",
                "2025-07-05T17:00:00Z",
                "2025-07-05T17:15:00Z",
                "2025-07-05T17:30:00Z",
                "2025-07-05T17:45:00Z",
                "2025-07-05T18:00:00Z",
                "2025-07-05T18:15:00Z",
                "2025-07-05T18:30:00Z",
                "2025-07-05T18:45:00Z",
                "2025-07-05T19:00:00Z",
                "2025-07-05T19:15:00Z",
                "2025-07-05T19:30:00Z",
                "2025-07-05T19:45:00Z",
                "2025-07-05T20:00:00Z",
                "2025-07-05T20:15:00Z",
                "2025-07-05T20:30:00Z",
                "2025-07-05T20:45:00Z",
                "2025-07-05T21:00:00Z",
                "2025-07-05T21:15:00Z",
                "2025-07-05T21:30:00Z",
                "2025-07-05T21:45:00Z",
                "2025-07-05T22:00:00Z",
                "2025-07-05T22:15:00Z",
                "2025-07-05T22:30:00Z",
                "2025-07-05T22:45:00Z",
                "2025-07-05T23:00:00Z",
                "2025-07-05T23:15:00Z",
                "2025-07-05T23:30:00Z",
                "2025-07-05T23:45:00Z",
                "2025-07-06T00:00:00Z",
                "2025-07-06T00:15:00Z",
                "2025-07-06T00:30:00Z",
                "2025-07-06T00:45:00Z",
                "2025-07-06T01:00:00Z",
                "2025-07-06T01:15:00Z",
                "2025-07-06T01:30:00Z",
                "2025-07-06T01:45:00Z",
                "2025-07-06T02:00:00Z",
                "2025-07-06T02:15:00Z",
                "2025-07-06T02:30:00Z",
                "2025-07-06T02:45:00Z",
                "2025-07-06T03:00:00Z",
                "2025-07-06T03:15:00Z",
                "2025-07-06T03:30:00Z",
                "2025-07-06T03:45:00Z",
                "2025-07-06T04:00:00Z",
                "2025-07-06T04:15:00Z",
                "2025-07-06T04:30:00Z",
                "2025-07-06T04:45:00Z",
                "2025-07-06T05:00:00Z",
                "2025-07-06T05:15:00Z",
                "2025-07-06T05:30:00Z",
                "2025-07-06T05:45:00Z",
                "2025-07-06T06:00:00Z",
                "2025-07-06T06:15:00Z",
                "2025-07-06T06:30:00Z",
                "2025-07-06T06:45:00Z",
                "2025-07-06T07:00:00Z",
                "2025-07-06T07:15:00Z",
                "2025-07-06T07:30:00Z",
                "2025-07-06T07:45:00Z",
                "2025-07-06T08:00:00Z",
                "2025-07-06T08:15:00Z",
                "2025-07-06T08:30:00Z",
                "2025-07-06T08:45:00Z",
                "2025-07-06T09:00:00Z",
                "2025-07-06T09:15:00Z",
                "2025-07-06T09:30:00Z",
                "2025-07-06T09:45:00Z",
                "2025-07-06T10:00:00Z",
                "2025-07-06T10:15:00Z",
                "2025-07-06T10:30:00Z",
                "2025-07-06T10:45:00Z",
                "2025-07-06T11:00:00Z",
                "2025-07-06T11:15:00Z",
                "2025-07-06T11:30:00Z",
                "2025-07-06T11:45:00Z",
                "2025-07-06T12:00:00Z",
                "2025-07-06T12:15:00Z",
                "2025-07-06T12:30:00Z",
                "2025-07-06T12:45:00Z",
                "2025-07-06T13:00:00Z",
                "2025-07-06T13:15:00Z",
                "2025-07-06T13:30:00Z",
                "2025-07-06T13:45:00Z",
                "2025-07-06T14:00:00Z",
                "2025-07-06T14:15:00Z",
                "2025-07-06T14:30:00Z",
                "2025-07-06T14:45:00Z",
                "2025-07-06T15:00:00Z",
                "2025-07-06T15:15:00Z",
                "2025-07-06T15:30:00Z",
                "2025-07-06T15:45:00Z",
                "2025-07-06T16:00:00Z",
                "2025-07-06T16:15:00Z",
                "2025-07-06T16:30:00Z",
                "2025-07-06T16:45:00Z",
                "2025-07-06T17:00:00Z",
                "2025-07-06T17:15:00Z",
                "2025-07-06T17:30:00Z",
                "2025-07-06T17:45:00Z",
                "2025-07-06T18:00:00Z",
                "2025-07-06T18:15:00Z",
                "2025-07-06T18:30:00Z",
                "2025-07-06T18:45:00Z",
                "2025-07-06T19:00:00Z",
                "2025-07-06T19:15:00Z",
                "2025-07-06T19:30:00Z",
                "2025-07-06T19:45:00Z",
                "2025-07-06T20:00:00Z",
                "2025-07-06T20:15:00Z",
                "2025-07-06T20:30:00Z",
                "2025-07-06T20:45:00Z",
                "2025-07-06T21:00:00Z",
                "2025-07-06T21:15:00Z",
                "2025-07-06T21:30:00Z",
                "2025-07-06T21:45:00Z",
                "2025-07-06T22:00:00Z",
                "2025-07-06T22:15:00Z",
                "2025-07-06T22:30:00Z",
                "2025-07-06T22:45:00Z",
                "2025-07-06T23:00:00Z",
                "2025-07-06T23:15:00Z",
                "2025-07-06T23:30:00Z",
                "2025-07-06T23:45:00Z",
                "2025-07-07T00:00:00Z",
                "2025-07-07T00:15:00Z",
                "2025-07-07T00:30:00Z",
                "2025-07-07T00:45:00Z",
                "2025-07-07T01:00:00Z",
                "2025-07-07T01:15:00Z",
                "2025-07-07T01:30:00Z",
                "2025-07-07T01:45:00Z",
                "2025-07-07T02:00:00Z",
                "2025-07-07T02:15:00Z",
                "2025-07-07T02:30:00Z",
                "2025-07-07T02:45:00Z",
                "2025-07-07T03:00:00Z",
                "2025-07-07T03:15:00Z",
                "2025-07-07T03:30:00Z",
                "2025-07-07T03:45:00Z",
                "2025-07-07T04:00:00Z",
                "2025-07-07T04:15:00Z",
                "2025-07-07T04:30:00Z",
                "2025-07-07T04:45:00Z",
                "2025-07-07T05:00:00Z",
                "2025-07-07T05:15:00Z",
                "2025-07-07T05:30:00Z",
                "2025-07-07T05:45:00Z",
                "2025-07-07T06:00:00Z",
                "2025-07-07T06:15:00Z",
                "2025-07-07T06:30:00Z",
                "2025-07-07T06:45:00Z",
                "2025-07-07T07:00:00Z",
                "2025-07-07T07:15:00Z",
                "2025-07-07T07:30:00Z",
                "2025-07-07T07:45:00Z",
                "2025-07-07T08:00:00Z",
                "2025-07-07T08:15:00Z",
                "2025-07-07T08:30:00Z",
                "2025-07-07T08:45:00Z",
                "2025-07-07T09:00:00Z",
                "2025-07-07T09:15:00Z",
                "2025-07-07T09:30:00Z",
                "2025-07-07T09:45:00Z",
                "2025-07-07T10:00:00Z",
                "2025-07-07T10:15:00Z",
                "2025-07-07T10:30:00Z",
                "2025-07-07T10:45:00Z",
                "2025-07-07T11:00:00Z",
                "2025-07-07T11:15:00Z",
                "2025-07-07T11:30:00Z",
                "2025-07-07T11:45:00Z",
                "2025-07-07T12:00:00Z",
                "2025-07-07T12:15:00Z",
                "2025-07-07T12:30:00Z",
                "2025-07-07T12:45:00Z",
                "2025-07-07T13:00:00Z",
                "2025-07-07T13:15:00Z",
                "2025-07-07T13:30:00Z"
            ],
            "values": [
                "0.674981",
                "0.678962",
                "0.695614",
                "0.6939",
                "0.666032",
                "0.707434",
                "0.665239",
                "0.691703",
                "0.691873",
                "0.704745",
                "0.755174",
                "0.683428",
                "0.705283",
                "0.675239",
                "0.718686",
                "0.72872",
                "0.709757",
                "0.718482",
                "0.746198",
                "0.768977",
                "0.773003",
                "0.799203",
                "0.857484",
                "0.882682",
                "0.849644",
                "0.875881",
                "0.883441",
                "0.912981",
                "0.960344",
                "0.873998",
                "0.910543",
                "0.944862",
                "0.888378",
                "0.788762",
                "0.739902",
                "0.728778",
                "0.656427",
                "0.63059",
                "0.587759",
                "0.546166",
                "0.498539",
                "0.45357",
                "0.396216",
                "0.371856",
                "0.347047",
                "0.301342",
                "0.265063",
                "0.235045",
                "0.229366",
                "0.209587",
                "0.190131",
                "0.168828",
                "0.171651",
                "0.167027",
                "0.144917",
                "0.148276",
                "0.143632",
                "0.16093",
                "0.145719",
                "0.157236",
                "0.176833",
                "0.175351",
                "0.196751",
                "0.208728",
                "0.23468",
                "0.255864",
                "0.269189",
                "0.326694",
                "0.323717",
                "0.361652",
                "0.359437",
                "0.432076",
                "0.410893",
                "0.454086",
                "0.459679",
                "0.495473",
                "0.527886",
                "0.540593",
                "0.661405",
                "0.589559",
                "0.614095",
                "0.660985",
                "0.658824",
                "0.65095",
                "0.723446",
                "0.737927",
                "0.762798",
                "0.708008",
                "0.739101",
                "0.714604",
                "0.748474",
                "0.721553",
                "0.821621",
                "0.751501",
                "0.747773",
                "0.748133",
                "0.728555",
                "0.73464",
                "0.75112",
                "0.784463",
                "0.71932",
                "0.74471",
                "0.77533",
                "0.715158",
                "0.736954",
                "0.719899",
                "0.693561",
                "0.730915",
                "0.716202",
                "0.699793",
                "0.77858",
                "0.721021",
                "0.745024",
                "0.767267",
                "0.760574",
                "0.788671",
                "0.810637",
                "0.875337",
                "0.846711",
                "0.856765",
                "0.903123",
                "0.906893",
                "0.950564",
                "0.912853",
                "0.851513",
                "0.921206",
                "0.850682",
                "0.822358",
                "0.772902",
                "0.764082",
                "0.709923",
                "0.656736",
                "0.647596",
                "0.590512",
                "0.501056",
                "0.459285",
                "0.415784",
                "0.382232",
                "0.346337",
                "0.316424",
                "0.29671",
                "0.255124",
                "0.242765",
                "0.206418",
                "0.190833",
                "0.184503",
                "0.165434",
                "0.15457",
                "0.160092",
                "0.144592",
                "0.143141",
                "0.138848",
                "0.142403",
                "0.148166",
                "0.155391",
                "0.159231",
                "0.175208",
                "0.180774",
                "0.197364",
                "0.21639",
                "0.234363",
                "0.274873",
                "0.292124",
                "0.297425",
                "0.323292",
                "0.350371",
                "0.370456",
                "0.380329",
                "0.399248",
                "0.421825",
                "0.476706",
                "0.473837",
                "0.478905",
                "0.496303",
                "0.507463",
                "0.524925",
                "0.541661",
                "0.55998",
                "0.648607",
                "0.602131",
                "0.597806",
                "0.611516",
                "0.618553",
                "0.625275",
                "0.665783",
                "0.715953",
                "0.661153",
                "0.667993",
                "0.659041",
                "0.668321",
                "0.67947",
                "0.661484"
            ]
        },
        "previous": {
            "timestamps": [
                "2025-06-28T13:45:00Z",
                "2025-06-28T14:00:00Z",
                "2025-06-28T14:15:00Z",
                "2025-06-28T14:30:00Z",
                "2025-06-28T14:45:00Z",
                "2025-06-28T15:00:00Z",
                "2025-06-28T15:15:00Z",
                "2025-06-28T15:30:00Z",
                "2025-06-28T15:45:00Z",
                "2025-06-28T16:00:00Z",
                "2025-06-28T16:15:00Z",
                "2025-06-28T16:30:00Z",
                "2025-06-28T16:45:00Z",
                "2025-06-28T17:00:00Z",
                "2025-06-28T17:15:00Z",
                "2025-06-28T17:30:00Z",
                "2025-06-28T17:45:00Z",
                "2025-06-28T18:00:00Z",
                "2025-06-28T18:15:00Z",
                "2025-06-28T18:30:00Z",
                "2025-06-28T18:45:00Z",
                "2025-06-28T19:00:00Z",
                "2025-06-28T19:15:00Z",
                "2025-06-28T19:30:00Z",
                "2025-06-28T19:45:00Z",
                "2025-06-28T20:00:00Z",
                "2025-06-28T20:15:00Z",
                "2025-06-28T20:30:00Z",
                "2025-06-28T20:45:00Z",
                "2025-06-28T21:00:00Z",
                "2025-06-28T21:15:00Z",
                "2025-06-28T21:30:00Z",
                "2025-06-28T21:45:00Z",
                "2025-06-28T22:00:00Z",
                "2025-06-28T22:15:00Z",
                "2025-06-28T22:30:00Z",
                "2025-06-28T22:45:00Z",
                "2025-06-28T23:00:00Z",
                "2025-06-28T23:15:00Z",
                "2025-06-28T23:30:00Z",
                "2025-06-28T23:45:00Z",
                "2025-06-29T00:00:00Z",
                "2025-06-29T00:15:00Z",
                "2025-06-29T00:30:00Z",
                "2025-06-29T00:45:00Z",
                "2025-06-29T01:00:00Z",
                "2025-06-29T01:15:00Z",
                "2025-06-29T01:30:00Z",
                "2025-06-29T01:45:00Z",
                "2025-06-29T02:00:00Z",
                "2025-06-29T02:15:00Z",
                "2025-06-29T02:30:00Z",
                "2025-06-29T02:45:00Z",
                "2025-06-29T03:00:00Z",
                "2025-06-29T03:15:00Z",
                "2025-06-29T03:30:00Z",
                "2025-06-29T03:45:00Z",
                "2025-06-29T04:00:00Z",
                "2025-06-29T04:15:00Z",
                "2025-06-29T04:30:00Z",
                "2025-06-29T04:45:00Z",
                "2025-06-29T05:00:00Z",
                "2025-06-29T05:15:00Z",
                "2025-06-29T05:30:00Z",
                "2025-06-29T05:45:00Z",
                "2025-06-29T06:00:00Z",
                "2025-06-29T06:15:00Z",
                "2025-06-29T06:30:00Z",
                "2025-06-29T06:45:00Z",
                "2025-06-29T07:00:00Z",
                "2025-06-29T07:15:00Z",
                "2025-06-29T07:30:00Z",
                "2025-06-29T07:45:00Z",
                "2025-06-29T08:00:00Z",
                "2025-06-29T08:15:00Z",
                "2025-06-29T08:30:00Z",
                "2025-06-29T08:45:00Z",
                "2025-06-29T09:00:00Z",
                "2025-06-29T09:15:00Z",
                "2025-06-29T09:30:00Z",
                "2025-06-29T09:45:00Z",
                "2025-06-29T10:00:00Z",
                "2025-06-29T10:15:00Z",
                "2025-06-29T10:30:00Z",
                "2025-06-29T10:45:00Z",
                "2025-06-29T11:00:00Z",
                "2025-06-29T11:15:00Z",
                "2025-06-29T11:30:00Z",
                "2025-06-29T11:45:00Z",
                "2025-06-29T12:00:00Z",
                "2025-06-29T12:15:00Z",
                "2025-06-29T12:30:00Z",
                "2025-06-29T12:45:00Z",
                "2025-06-29T13:00:00Z",
                "2025-06-29T13:15:00Z",
                "2025-06-29T13:30:00Z",
                "2025-06-29T13:45:00Z",
                "2025-06-29T14:00:00Z",
                "2025-06-29T14:15:00Z",
                "2025-06-29T14:30:00Z",
                "2025-06-29T14:45:00Z",
                "2025-06-29T15:00:00Z",
                "2025-06-29T15:15:00Z",
                "2025-06-29T15:30:00Z",
                "2025-06-29T15:45:00Z",
                "2025-06-29T16:00:00Z",
                "2025-06-29T16:15:00Z",
                "2025-06-29T16:30:00Z",
                "2025-06-29T16:45:00Z",
                "2025-06-29T17:00:00Z",
                "2025-06-29T17:15:00Z",
                "2025-06-29T17:30:00Z",
                "2025-06-29T17:45:00Z",
                "2025-06-29T18:00:00Z",
                "2025-06-29T18:15:00Z",
                "2025-06-29T18:30:00Z",
                "2025-06-29T18:45:00Z",
                "2025-06-29T19:00:00Z",
                "2025-06-29T19:15:00Z",
                "2025-06-29T19:30:00Z",
                "2025-06-29T19:45:00Z",
                "2025-06-29T20:00:00Z",
                "2025-06-29T20:15:00Z",
                "2025-06-29T20:30:00Z",
                "2025-06-29T20:45:00Z",
                "2025-06-29T21:00:00Z",
                "2025-06-29T21:15:00Z",
                "2025-06-29T21:30:00Z",
                "2025-06-29T21:45:00Z",
                "2025-06-29T22:00:00Z",
                "2025-06-29T22:15:00Z",
                "2025-06-29T22:30:00Z",
                "2025-06-29T22:45:00Z",
                "2025-06-29T23:00:00Z",
                "2025-06-29T23:15:00Z",
                "2025-06-29T23:30:00Z",
                "2025-06-29T23:45:00Z",
                "2025-06-30T00:00:00Z",
                "2025-06-30T00:15:00Z",
                "2025-06-30T00:30:00Z",
                "2025-06-30T00:45:00Z",
                "2025-06-30T01:00:00Z",
                "2025-06-30T01:15:00Z",
                "2025-06-30T01:30:00Z",
                "2025-06-30T01:45:00Z",
                "2025-06-30T02:00:00Z",
                "2025-06-30T02:15:00Z",
                "2025-06-30T02:30:00Z",
                "2025-06-30T02:45:00Z",
                "2025-06-30T03:00:00Z",
                "2025-06-30T03:15:00Z",
                "2025-06-30T03:30:00Z",
                "2025-06-30T03:45:00Z",
                "2025-06-30T04:00:00Z",
                "2025-06-30T04:15:00Z",
                "2025-06-30T04:30:00Z",
                "2025-06-30T04:45:00Z",
                "2025-06-30T05:00:00Z",
                "2025-06-30T05:15:00Z",
                "2025-06-30T05:30:00Z",
                "2025-06-30T05:45:00Z",
                "2025-06-30T06:00:00Z",
                "2025-06-30T06:15:00Z",
                "2025-06-30T06:30:00Z",
                "2025-06-30T06:45:00Z",
                "2025-06-30T07:00:00Z",
                "2025-06-30T07:15:00Z",
                "2025-06-30T07:30:00Z",
                "2025-06-30T07:45:00Z",
                "2025-06-30T08:00:00Z",
                "2025-06-30T08:15:00Z",
                "2025-06-30T08:30:00Z",
                "2025-06-30T08:45:00Z",
                "2025-06-30T09:00:00Z",
                "2025-06-30T09:15:00Z",
                "2025-06-30T09:30:00Z",
                "2025-06-30T09:45:00Z",
                "2025-06-30T10:00:00Z",
                "2025-06-30T10:15:00Z",
                "2025-06-30T10:30:00Z",
                "2025-06-30T10:45:00Z",
                "2025-06-30T11:00:00Z",
                "2025-06-30T11:15:00Z",
                "2025-06-30T11:30:00Z",
                "2025-06-30T11:45:00Z",
                "2025-06-30T12:00:00Z",
                "2025-06-30T12:15:00Z",
                "2025-06-30T12:30:00Z",
                "2025-06-30T12:45:00Z",
                "2025-06-30T13:00:00Z",
                "2025-06-30T13:15:00Z",
                "2025-06-30T13:30:00Z"
            ],
            "values": [
                "0.769524",
                "0.714683",
                "0.741507",
                "0.724216",
                "0.718082",
                "0.733913",
                "0.730172",
                "0.736627",
                "0.692905",
                "0.690326",
                "0.692727",
                "0.692727",
                "0.733971",
                "0.708706",
                "0.697044",
                "0.72176",
                "0.711722",
                "0.73624",
                "0.796099",
                "0.82192",
                "0.815619",
                "0.838946",
                "0.833419",
                "0.846131",
                "0.858626",
                "0.870599",
                "0.902173",
                "0.932302",
                "0.996988",
                "0.868179",
                "0.888472",
                "0.90529",
                "0.835299",
                "0.894889",
                "0.828066",
                "0.735053",
                "0.664279",
                "0.677828",
                "0.65096",
                "0.567609",
                "0.48684",
                "0.475278",
                "0.404802",
                "0.393016",
                "0.339663",
                "0.298534",
                "0.269414",
                "0.246969",
                "0.233401",
                "0.205518",
                "0.196192",
                "0.181057",
                "0.174119",
                "0.175957",
                "0.160059",
                "0.157362",
                "0.155626",
                "0.158672",
                "0.158164",
                "0.167244",
                "0.185937",
                "0.199823",
                "0.218607",
                "0.245956",
                "0.236192",
                "0.265017",
                "0.273883",
                "0.31369",
                "0.320809",
                "0.35668",
                "0.37257",
                "0.400838",
                "0.440964",
                "0.451329",
                "0.476497",
                "0.554745",
                "0.557223",
                "0.565709",
                "0.611431",
                "0.61045",
                "0.675263",
                "0.697851",
                "0.691693",
                "0.724233",
                "0.730081",
                "0.713781",
                "0.734003",
                "0.759998",
                "0.797232",
                "0.878579",
                "0.775156",
                "0.780106",
                "0.795186",
                "0.811512",
                "0.778065",
                "0.773048",
                "0.8053",
                "0.763123",
                "0.784061",
                "0.761709",
                "0.791559",
                "0.76646",
                "0.769928",
                "0.791821",
                "0.766731",
                "0.771003",
                "0.770455",
                "0.756216",
                "0.753648",
                "0.757444",
                "0.778463",
                "0.855883",
                "0.835891",
                "0.827763",
                "0.857009",
                "0.868635",
                "0.901049",
                "0.939507",
                "0.965731",
                "0.913308",
                "0.921557",
                "1.0",
                "0.947868",
                "0.93944",
                "0.906642",
                "0.8878",
                "0.871038",
                "0.84511",
                "0.802386",
                "0.793484",
                "0.719343",
                "0.673714",
                "0.734035",
                "0.573746",
                "0.501072",
                "0.476738",
                "0.438084",
                "0.400407",
                "0.380515",
                "0.333508",
                "0.302711",
                "0.253514",
                "0.229702",
                "0.214532",
                "0.200325",
                "0.176216",
                "0.163959",
                "0.152929",
                "0.159818",
                "0.138841",
                "0.146014",
                "0.157209",
                "0.150282",
                "0.141725",
                "0.160263",
                "0.155022",
                "0.169596",
                "0.184845",
                "0.194363",
                "0.226225",
                "0.242124",
                "0.256514",
                "0.289141",
                "0.297093",
                "0.336746",
                "0.379929",
                "0.374761",
                "0.400653",
                "0.422977",
                "0.430304",
                "0.45032",
                "0.479332",
                "0.553647",
                "0.526586",
                "0.54429",
                "0.540843",
                "0.557095",
                "0.613548",
                "0.636154",
                "0.62906",
                "0.679025",
                "0.675934",
                "0.666371",
                "0.639914",
                "0.663022",
                "0.661692",
                "0.685056",
                "0.673789",
                "0.681274",
                "0.687801",
                "0.655927",
                "0.690624"
            ]
        },
        "meta": {
            "dateRange": [
                {
                    "startTime": "2025-07-05T13:45:00Z",
                    "endTime": "2025-07-07T13:45:00Z"
                },
                {
                    "startTime": "2025-06-28T13:45:00Z",
                    "endTime": "2025-06-30T13:45:00Z"
                }
            ],
            "confidenceInfo": {
                "level": 5,
                "annotations": []
            },
            "normalization": "MIN0_MAX",
            "aggInterval": "FIFTEEN_MINUTES",
            "lastUpdated": "2025-07-07T13:30:00Z",
            "units": [
                {
                    "name": "*",
                    "value": "bytes"
                }
            ]
        }
    }
}