{
    "success": true,
    "errors": [],
    "result": {
        "main": {
            "timestamps": [
                "2025-07-05T13:45:00Z",
                "2025-07-05T14:00:00Z",
                "2025-07-05T14:15:00Z",
                "2025-07-05T14:30:00Z",
                "2025-07-05T14:45:00Z",
                "2025-07-05T15:00:00Z",
                "2025-07-05T15:15:00Z",
                "2025-07-05T15:30:00Z",
                "2025-07-05T15:45:00Z",
                "2025-07-05T16:00:00Z",
                "2025-07-05T16:15:00Z",
                "2025-07-05T16:30:00Z",
                "2025-07-05T16:45:00Z",
                "2025-07-05T17:00:00Z",
                "2025-07-05T17:15:00Z",
                "2025-07-05T17:30:00Z",
                "2025-07-05T17:45:00Z",
                "2025-07-05T18:00:00Z",
                "2025-07-05T18:15:00Z",
                "2025-07-05T18:30:00Z",
                "2025-07-05T18:45:00Z",
                "2025-07-05T19:00:00Z",
                "2025-07-05T19:15:00Z",
                "2025-07-05T19:30:00Z",
                "2025-07-05T19:45:00Z",
                "2025-07-05T20:00:00Z",
                "2025-07-05T20:15:00Z",
                "2025-07-05T20:30:00Z",
                "2025-07-05T20:45:00Z",
                "2025-07-05T21:00:00Z",
                "2025-07-05T21:15:00Z",
                "2025-07-05T21:30:00Z",
                "2025-07-05T21:45:00Z",
                "2025-07-05T22:00:00Z",
                "2025-07-05T22:15:00Z",
                "2025-07-05T22:30:00Z",
                "2025-07-05T22:45:00Z",
                "2025-07-05T23:00:00Z",
                "2025-07-05T23:15:00Z",
                "2025-07-05T23:30:00Z",
                "2025-07-05T23:45:00Z",
                "2025-07-06T00:00:00Z",
                "2025-07-06T00:15:00Z",
                "2025-07-06T00:30:00Z",
                "2025-07-06T00:45:00Z",
                "2025-07-06T01:00:00Z",
                "2025-07-06T01:15:00Z",
                "2025-07-06T01:30:00Z",
                "2025-07-06T01:45:00Z",
                "2025-07-06T02:00:00Z",
                "2025-07-06T02:15:00Z",
                "2025-07-06T02:30:00Z",
                "2025-07-06T02:45:00Z",
                "2025-07-06T03:00:00Z",
                "2025-07-06T03:15:00Z",
                "2025-07-06T03:30:00Z",
                "2025-07-06T03:45:00Z",
                "2025-07-06T04:00:00Z",
                "2025-07-06T04:15:00Z",
                "2025-07-06T04:30:00Z",
                "2025-07-06T04:45:00Z",
                "2025-07-06T05:00:00Z",
                "2025-07-06T05:15:00Z",
                "2025-07-06T05:30:00Z",
                "2025-07-06T05:45:00Z",
                "2025-07-06T06:00:00Z",
                "2025-07-06T06:15:00Z",
                "2025-07-06T06:30:00Z",
                "2025-07-06T06:45:00Z",
                "2025-07-06T07:00:00Z",
                "2025-07-06T07:15:00Z",
                "2025-07-06T07:30:00Z",
                "2025-07-06T07:45:00Z",
                "2025-07-06T08:00:00Z",
                "2025-07-06T08:15:00Z",
                "2025-07-06T08:30:00Z",
                "2025-07-06T08:45:00Z",
                "2025-07-06T09:00:00Z",
                "2025-07-06T09:15:00Z",
                "2025-07-06T09:30:00Z",
                "2025-07-06T09:45:00Z",
                "2025-07-06T10:00:00Z",
                "2025-07-06T10:15:00Z",
                "2025-07-06T10:30:00Z",
                "2025-07-06T10:45:00Z",
                "2025-07-06T11:00:00Z",
                "2025-07-06T11:15:00Z",
                "2025-07-06T11:30:00Z",
                "2025-07-06T11:45:00Z",
                "2025-07-06T12:00:00Z",
                "2025-07-06T12:15:00Z",
                "2025-07-06T12:30:00Z",
                "2025-07-06T12:45:00Z",
                "2025-07-06T13:00:00Z",
                "2025-07-06T13:15:00Z",
                "2025-07-06T13:30:00Z",
                "2025-07-06T13:45:00Z",
                "2025-07-06T14:00:00Z",
                "2025-07-06T14:15:00Z",
                "2025-07-06T14:30:00Z",
                "2025-07-06T14:45:00Z",
                "2025-07-06T15:00:00Z",
                "2025-07-06T15:15:00Z",
                "2025-07-06T15:30:00Z",
                "2025-07-06T15:45:00Z",
                "2025-07-06T16:00:00Z",
                "2025-07-06T16:15:00Z",
                "2025-07-06T16:30:00Z",
                "2025-07-06T16:45:00Z",
                "2025-07-06T17:00:00Z",
                "2025-07-06T17:15:00Z",
                "2025-07-06T17:30:00Z",
                "2025-07-06T17:45:00Z",
                "2025-07-06T18:00:00Z",
                "2025-07-06T18:15:00Z",
                "2025-07-06T18:30:00Z",
                "2025-07-06T18:45:00Z",
                "2025-07-06T19:00:00Z",
                "2025-07-06T19:15:00Z",
                "2025-07-06T19:30:00Z",
                "2025-07-06T19:45:00Z",
                "2025-07-06T20:00:00Z",
                "2025-07-06T20:15:00Z",
                "2025-07-06T20:30:00Z",
                "2025-07-06T20:45:00Z",
                "2025-07-06T21:00:00Z",
                "2025-07-06T21:15:00Z",
                "2025-07-06T21:30:00Z",
                "2025-07-06T21:45:00Z",
                "2025-07-06T22:00:00Z",
                "2025-07-06T22:15:00Z",
                "2025-07-06T22:30:00Z",
                "2025-07-06T22:45:00Z",
                "2025-07-06T23:00:00Z",
                "2025-07-06T23:15:00Z",
                "2025-07-06T23:30:00Z",
                "2025-07-06T23:45:00Z",
                "2025-07-07T00:00:00Z",
                "2025-07-07T00:15:00Z",
                "2025-07-07T00:30:00Z",
                "2025-07-07T00:45:00Z",
                "2025-07-07T01:00:00Z",
                "2025-07-07T01:15:00Z",
                "2025-07-07T01:30:00Z",
                "2025-07-07T01:45:00Z",
                "2025-07-07T02:00:00Z",
                "2025-07-07T02:15:00Z",
                "2025-07-07T02:30:00Z",
                "2025-07-07T02:45:00Z",
                "2025-07-07T03:00:00Z",
                "2025-07-07T03:15:00Z",
                "2025-07-07T03:30:00Z",
                "2025-07-07T03:45:00Z",
                "2025-07-07T04:00:00Z",
                "2025-07-07T04:15:00Z",
                "2025-07-07T04:30:00Z",
                "2025-07-07T04:45:00Z",
                "2025-07-07T05:00:00Z",
                "2025-07-07T05:15:00Z",
                "2025-07-07T05:30:00Z",
                "2025-07-07T05:45:00Z",
                "2025-07-07T06:00:00Z",
                "2025-07-07T06:15:00Z",
                "2025-07-07T06:30:00Z",
                "2025-07-07T06:45:00Z",
                "2025-07-07T07:00:00Z",
                "2025-07-07T07:15:00Z",
                "2025-07-07T07:30:00Z",
                "2025-07-07T07:45:00Z",
                "2025-07-07T08:00:00Z",
                "2025-07-07T08:15:00Z",
                "2025-07-07T08:30:00Z",
                "2025-07-07T08:45:00Z",
                "2025-07-07T09:00:00Z",
                "2025-07-07T09:15:00Z",
                "2025-07-07T09:30:00Z",
                "2025-07-07T09:45:00Z",
                "2025-07-07T10:00:00Z",
                "2025-07-07T10:15:00Z",
                "2025-07-07T10:30:00Z",
                "2025-07-07T10:45:00Z",
                "2025-07-07T11:00:00Z",
                "2025-07-07T11:15:00Z",
                "2025-07-07T11:30:00Z",
                "2025-07-07T11:45:00Z",
                "2025-07-07T12:00:00Z",
                "2025-07-07T12:15:00Z",
                "2025-07-07T12:30:00Z",
                "2025-07-07T12:45:00Z",
                "2025-07-07T13:00:00Z",
                "2025-07-07T13:15:00Z",
                "2025-07-07T13:30:00Z"
            ],
            "values": [
                "0.582246",
                "0.582112",
                "0.610356",
                "0.629524",
                "0.616932",
                "0.644656",
                "0.556253",
                "0.500849",
                "0.593799",
                "0.758487",
                "0.938693",
                "0.880438",
                "0.810033",
                "0.71459",
                "0.909627",
                "0.9112",
                "1.0",
                "0.82152",
                "0.632746",
                "0.600469",
                "0.570801",
                "0.603625",
                "0.614372",
                "0.628284",
                "0.60194",
                "0.763265",
                "0.813325",
                "0.809782",
                "0.728466",
                "0.63009",
                "0.68947",
                "0.7006",
                "0.640928",
                "0.443699",
                "0.376985",
                "0.348756",
                "0.301943",
                "0.282102",
                "0.256997",
                "0.234324",
                "0.211623",
                "0.198261",
                "0.180483",
                "0.168844",
                "0.166839",
                "0.151037",
                "0.138858",
                "0.131514",
                "0.13562",
                "0.13066",
                "0.129256",
                "0.125592",
                "0.145808",
                "0.165582",
                "0.164425",
                "0.184985",
                "0.198975",
                "0.245739",
                "0.247898",
                "0.282267",
                "0.325223",
                "0.312631",
                "0.351841",
                "0.353737",
                "0.376835",
                "0.404386",
                "0.405254",
                "0.468046",
                "0.441101",
                "0.469272",
                "0.43882",
                "0.510566",
                "0.470786",
                "0.504433",
                "0.490457",
                "0.505919",
                "0.500212",
                "0.499446",
                "0.605293",
                "0.537623",
                "0.544712",
                "0.557224",
                "0.547303",
                "0.521729",
                "0.572265",
                "0.563554",
                "0.599937",
                "0.539737",
                "0.564648",
                "0.550628",
                "0.562673",
                "0.539524",
                "0.56144",
                "0.56795",
                "0.574358",
                "0.574923",
                "0.565869",
                "0.563137",
                "0.581086",
                "0.54217",
                "0.556775",
                "0.592076",
                "0.594521",
                "0.538836",
                "0.504517",
                "0.538145",
                "0.553372",
                "0.580152",
                "0.570128",
                "0.551518",
                "0.554936",
                "0.558556",
                "0.588406",
                "0.586826",
                "0.501459",
                "0.558669",
                "0.551276",
                "0.587085",
                "0.54357",
                "0.505682",
                "0.566688",
                "0.551223",
                "0.572381",
                "0.545923",
                "0.498988",
                "0.521281",
                "0.415075",
                "0.422615",
                "0.375365",
                "0.360398",
                "0.321236",
                "0.294465",
                "0.284452",
                "0.258015",
                "0.22699",
                "0.209426",
                "0.188106",
                "0.172537",
                "0.160371",
                "0.144013",
                "0.146683",
                "0.139155",
                "0.133996",
                "0.119127",
                "0.117702",
                "0.121966",
                "0.122429",
                "0.125112",
                "0.144338",
                "0.148058",
                "0.164986",
                "0.179637",
                "0.20085",
                "0.231412",
                "0.252703",
                "0.281155",
                "0.322588",
                "0.327511",
                "0.340779",
                "0.365249",
                "0.384678",
                "0.442816",
                "0.457322",
                "0.446796",
                "0.465459",
                "0.504561",
                "0.486328",
                "0.489437",
                "0.501835",
                "0.516269",
                "0.573119",
                "0.544702",
                "0.534915",
                "0.546371",
                "0.554846",
                "0.548961",
                "0.56253",
                "0.576801",
                "0.654764",
                "0.593736",
                "0.572251",
                "0.578352",
                "0.571731",
                "0.577826",
                "0.614533",
                "0.64975",
                "0.579312",
                "0.583341",
                "0.582425",
                "0.587523",
                "0.598174",
                "0.591426"
            ]
        },
        "previous": {
            "timestamps": [
                "2025-06-28T13:45:00Z",
                "2025-06-28T14:00:00Z",
                "2025-06-28T14:15:00Z",
                "2025-06-28T14:30:00Z",
                "2025-06-28T14:45:00Z",
                "2025-06-28T15:00:00Z",
                "2025-06-28T15:15:00Z",
                "2025-06-28T15:30:00Z",
                "2025-06-28T15:45:00Z",
                "2025-06-28T16:00:00Z",
                "2025-06-28T16:15:00Z",
                "2025-06-28T16:30:00Z",
                "2025-06-28T16:45:00Z",
                "2025-06-28T17:00:00Z",
                "2025-06-28T17:15:00Z",
                "2025-06-28T17:30:00Z",
                "2025-06-28T17:45:00Z",
                "2025-06-28T18:00:00Z",
                "2025-06-28T18:15:00Z",
                "2025-06-28T18:30:00Z",
                "2025-06-28T18:45:00Z",
                "2025-06-28T19:00:00Z",
                "2025-06-28T19:15:00Z",
                "2025-06-28T19:30:00Z",
                "2025-06-28T19:45:00Z",
                "2025-06-28T20:00:00Z",
                "2025-06-28T20:15:00Z",
                "2025-06-28T20:30:00Z",
                "2025-06-28T20:45:00Z",
                "2025-06-28T21:00:00Z",
                "2025-06-28T21:15:00Z",
                "2025-06-28T21:30:00Z",
                "2025-06-28T21:45:00Z",
                "2025-06-28T22:00:00Z",
                "2025-06-28T22:15:00Z",
                "2025-06-28T22:30:00Z",
                "2025-06-28T22:45:00Z",
                "2025-06-28T23:00:00Z",
                "2025-06-28T23:15:00Z",
                "2025-06-28T23:30:00Z",
                "2025-06-28T23:45:00Z",
                "2025-06-29T00:00:00Z",
                "2025-06-29T00:15:00Z",
                "2025-06-29T00:30:00Z",
                "2025-06-29T00:45:00Z",
                "2025-06-29T01:00:00Z",
                "2025-06-29T01:15:00Z",
                "2025-06-29T01:30:00Z",
                "2025-06-29T01:45:00Z",
                "2025-06-29T02:00:00Z",
                "2025-06-29T02:15:00Z",
                "2025-06-29T02:30:00Z",
                "2025-06-29T02:45:00Z",
                "2025-06-29T03:00:00Z",
                "2025-06-29T03:15:00Z",
                "2025-06-29T03:30:00Z",
                "2025-06-29T03:45:00Z",
                "2025-06-29T04:00:00Z",
                "2025-06-29T04:15:00Z",
                "2025-06-29T04:30:00Z",
                "2025-06-29T04:45:00Z",
                "2025-06-29T05:00:00Z",
                "2025-06-29T05:15:00Z",
                "2025-06-29T05:30:00Z",
                "2025-06-29T05:45:00Z",
                "2025-06-29T06:00:00Z",
                "2025-06-29T06:15:00Z",
                "2025-06-29T06:30:00Z",
                "2025-06-29T06:45:00Z",
                "2025-06-29T07:00:00Z",
                "2025-06-29T07:15:00Z",
                "2025-06-29T07:30:00Z",
                "2025-06-29T07:45:00Z",
                "2025-06-29T08:00:00Z",
                "2025-06-29T08:15:00Z",
                "2025-06-29T08:30:00Z",
                "2025-06-29T08:45:00Z",
                "2025-06-29T09:00:00Z",
                "2025-06-29T09:15:00Z",
                "2025-06-29T09:30:00Z",
                "2025-06-29T09:45:00Z",
                "2025-06-29T10:00:00Z",
                "2025-06-29T10:15:00Z",
                "2025-06-29T10:30:00Z",
                "2025-06-29T10:45:00Z",
                "2025-06-29T11:00:00Z",
                "2025-06-29T11:15:00Z",
                "2025-06-29T11:30:00Z",
                "2025-06-29T11:45:00Z",
                "2025-06-29T12:00:00Z",
                "2025-06-29T12:15:00Z",
                "2025-06-29T12:30:00Z",
                "2025-06-29T12:45:00Z",
                "2025-06-29T13:00:00Z",
                "2025-06-29T13:15:00Z",
                "2025-06-29T13:30:00Z",
                "2025-06-29T13:45:00Z",
                "2025-06-29T14:00:00Z",
                "2025-06-29T14:15:00Z",
                "2025-06-29T14:30:00Z",
                "2025-06-29T14:45:00Z",
                "2025-06-29T15:00:00Z",
                "2025-06-29T15:15:00Z",
                "2025-06-29T15:30:00Z",
                "2025-06-29T15:45:00Z",
                "2025-06-29T16:00:00Z",
                "2025-06-29T16:15:00Z",
                "2025-06-29T16:30:00Z",
                "2025-06-29T16:45:00Z",
                "2025-06-29T17:00:00Z",
                "2025-06-29T17:15:00Z",
                "2025-06-29T17:30:00Z",
                "2025-06-29T17:45:00Z",
                "2025-06-29T18:00:00Z",
                "2025-06-29T18:15:00Z",
                "2025-06-29T18:30:00Z",
                "2025-06-29T18:45:00Z",
                "2025-06-29T19:00:00Z",
                "2025-06-29T19:15:00Z",
                "2025-06-29T19:30:00Z",
                "2025-06-29T19:45:00Z",
                "2025-06-29T20:00:00Z",
                "2025-06-29T20:15:00Z",
                "2025-06-29T20:30:00Z",
                "2025-06-29T20:45:00Z",
                "2025-06-29T21:00:00Z",
                "2025-06-29T21:15:00Z",
                "2025-06-29T21:30:00Z",
                "2025-06-29T21:45:00Z",
                "2025-06-29T22:00:00Z",
                "2025-06-29T22:15:00Z",
                "2025-06-29T22:30:00Z",
                "2025-06-29T22:45:00Z",
                "2025-06-29T23:00:00Z",
                "2025-06-29T23:15:00Z",
                "2025-06-29T23:30:00Z",
                "2025-06-29T23:45:00Z",
                "2025-06-30T00:00:00Z",
                "2025-06-30T00:15:00Z",
                "2025-06-30T00:30:00Z",
                "2025-06-30T00:45:00Z",
                "2025-06-30T01:00:00Z",
                "2025-06-30T01:15:00Z",
                "2025-06-30T01:30:00Z",
                "2025-06-30T01:45:00Z",
                "2025-06-30T02:00:00Z",
                "2025-06-30T02:15:00Z",
                "2025-06-30T02:30:00Z",
                "2025-06-30T02:45:00Z",
                "2025-06-30T03:00:00Z",
                "2025-06-30T03:15:00Z",
                "2025-06-30T03:30:00Z",
                "2025-06-30T03:45:00Z",
                "2025-06-30T04:00:00Z",
                "2025-06-30T04:15:00Z",
                "2025-06-30T04:30:00Z",
                "2025-06-30T04:45:00Z",
                "2025-06-30T05:00:00Z",
                "2025-06-30T05:15:00Z",
                "2025-06-30T05:30:00Z",
                "2025-06-30T05:45:00Z",
                "2025-06-30T06:00:00Z",
                "2025-06-30T06:15:00Z",
                "2025-06-30T06:30:00Z",
                "2025-06-30T06:45:00Z",
                "2025-06-30T07:00:00Z",
                "2025-06-30T07:15:00Z",
                "2025-06-30T07:30:00Z",
                "2025-06-30T07:45:00Z",
                "2025-06-30T08:00:00Z",
                "2025-06-30T08:15:00Z",
                "2025-06-30T08:30:00Z",
                "2025-06-30T08:45:00Z",
                "2025-06-30T09:00:00Z",
                "2025-06-30T09:15:00Z",
                "2025-06-30T09:30:00Z",
                "2025-06-30T09:45:00Z",
                "2025-06-30T10:00:00Z",
                "2025-06-30T10:15:00Z",
                "2025-06-30T10:30:00Z",
                "2025-06-30T10:45:00Z",
                "2025-06-30T11:00:00Z",
                "2025-06-30T11:15:00Z",
                "2025-06-30T11:30:00Z",
                "2025-06-30T11:45:00Z",
                "2025-06-30T12:00:00Z",
                "2025-06-30T12:15:00Z",
                "2025-06-30T12:30:00Z",
                "2025-06-30T12:45:00Z",
                "2025-06-30T13:00:00Z",
                "2025-06-30T13:15:00Z",
                "2025-06-30T13:30:00Z"
            ],
            "values": [
                "0.608488",
                "0.557781",
                "0.584527",
                "0.577936",
                "0.58049",
                "0.581388",
                "0.572471",
                "0.57072",
                "0.554095",
                "0.579927",
                "0.593985",
                "0.602528",
                "0.617898",
                "0.581571",
                "0.602576",
                "0.638376",
                "0.629992",
                "0.632422",
                "0.644503",
                "0.647874",
                "0.602572",
                "0.6",
                "0.594172",
                "0.592006",
                "0.575059",
                "0.647812",
                "0.691781",
                "0.711834",
                "0.686687",
                "0.560999",
                "0.627775",
                "0.636954",
                "0.543329",
                "0.480547",
                "0.423417",
                "0.354882",
                "0.313133",
                "0.306609",
                "0.277015",
                "0.247254",
                "0.223962",
                "0.23244",
                "0.200788",
                "0.203414",
                "0.177595",
                "0.156294",
                "0.148821",
                "0.141985",
                "0.138748",
                "0.133279",
                "0.135556",
                "0.136075",
                "0.147987",
                "0.167545",
                "0.17367",
                "0.189089",
                "0.218033",
                "0.246148",
                "0.258878",
                "0.276544",
                "0.311197",
                "0.343651",
                "0.365319",
                "0.333014",
                "0.280792",
                "0.298612",
                "0.286925",
                "0.306181",
                "0.303997",
                "0.311997",
                "0.304415",
                "0.30822",
                "0.346654",
                "0.360313",
                "0.358557",
                "0.409783",
                "0.419373",
                "0.41156",
                "0.457258",
                "0.452909",
                "0.500138",
                "0.510553",
                "0.497091",
                "0.524307",
                "0.525426",
                "0.508625",
                "0.511127",
                "0.516013",
                "0.537453",
                "0.596158",
                "0.538526",
                "0.543062",
                "0.550772",
                "0.577498",
                "0.543905",
                "0.551721",
                "0.576217",
                "0.545167",
                "0.56559",
                "0.54576",
                "0.572548",
                "0.544741",
                "0.556939",
                "0.561531",
                "0.552921",
                "0.633579",
                "0.671709",
                "0.660409",
                "0.603548",
                "0.599163",
                "0.649631",
                "0.716425",
                "0.669287",
                "0.598324",
                "0.580454",
                "0.527389",
                "0.583938",
                "0.594851",
                "0.592739",
                "0.527803",
                "0.525478",
                "0.608844",
                "0.586336",
                "0.565485",
                "0.532332",
                "0.508243",
                "0.484772",
                "0.460975",
                "0.421953",
                "0.390786",
                "0.329517",
                "0.304658",
                "0.310023",
                "0.249097",
                "0.222757",
                "0.202701",
                "0.180268",
                "0.176573",
                "0.172517",
                "0.146739",
                "0.142236",
                "0.131017",
                "0.121497",
                "0.127892",
                "0.127864",
                "0.122749",
                "0.128594",
                "0.133232",
                "0.151111",
                "0.147667",
                "0.175358",
                "0.218415",
                "0.240918",
                "0.235092",
                "0.284883",
                "0.286145",
                "0.33617",
                "0.365182",
                "0.38146",
                "0.432779",
                "0.431713",
                "0.446904",
                "0.480519",
                "0.472898",
                "0.509363",
                "0.555351",
                "0.506373",
                "0.542009",
                "0.558031",
                "0.542423",
                "0.554318",
                "0.567121",
                "0.630232",
                "0.589799",
                "0.584555",
                "0.564841",
                "0.561654",
                "0.603294",
                "0.604357",
                "0.58777",
                "0.621158",
                "0.617039",
                "0.607917",
                "0.581511",
                "0.599896",
                "0.595623",
                "0.627912",
                "0.615847",
                "0.606283",
                "0.606573",
                "0.577025",
                "0.621022"
            ]
        },
        "meta": {
            "dateRange": [
                {
                    "startTime": "2025-07-05T13:45:00Z",
                    "endTime": "2025-07-07T13:45:00Z"
                },
                {
                    "startTime": "2025-06-28T13:45:00Z",
                    "endTime": "2025-06-30T13:45:00Z"
                }
            ],
            "confidenceInfo": {
                "level": 5,
                "annotations": []
            },
            "normalization": "MIN0_MAX",
            "aggInterval": "FIFTEEN_MINUTES",
            "lastUpdated": "2025-07-07T13:30:00Z",
            "units": [
                {
                    "name": "*",
                    "value": "bytes"
                }
            ]
        }
    }
}